pyubbink/__init__.py
pyubbink-0.1.dist-info/LICENSE
pyubbink-0.1.dist-info/METADATA
pyubbink-0.1.dist-info/WHEEL
pyubbink-0.1.dist-info/top_level.txt
pyubbink-0.1.dist-info/RECORD
