Metadata-Version: 2.1
Name: pyubbink
Version: 0.1
Summary: Python interface for Ubbink Ubiflux Vigor ventillation
Home-page: https://github.com/asillye/pyubbink
Author: Adam Sillye
Author-email: adam@berriesand.co
License: MIT
Platform: any
Classifier: Development Status :: 4 - Beta
Classifier: Intended Audience :: Developers
Classifier: Topic :: Software Development :: Build Tools
Classifier: License :: OSI Approved :: MIT License
Classifier: Programming Language :: Python :: 3
Classifier: Operating System :: OS Independent
License-File: LICENSE
Requires-Dist: pymodbus
